MisSER/__init__.py
MisSER/block_class.py
MisSER/find_small_exon.py
MisSER/fix_small_exon_multiproc.py
MisSER/run_misser.py
MisSER/version.py
MisSER-0.0.6.dist-info/LICENSE
MisSER-0.0.6.dist-info/METADATA
MisSER-0.0.6.dist-info/WHEEL
MisSER-0.0.6.dist-info/entry_points.txt
MisSER-0.0.6.dist-info/top_level.txt
MisSER-0.0.6.dist-info/RECORD
