Metadata-Version: 2.1
Name: MisSER
Version: 0.0.6
Summary: Find and fix missed small exons.
Home-page: https://github.com/zhenLiuExplr/MisSER-project
Author: Zhen Liu
Author-email: liuzhen2018@sibs.ac.cn
License: UNKNOWN
Platform: UNKNOWN
Classifier: Programming Language :: Python :: 3
Classifier: License :: OSI Approved :: MIT License
Classifier: Operating System :: POSIX :: Linux
Requires-Python: >=3
License-File: LICENSE
Requires-Dist: numpy
Requires-Dist: pandas
Requires-Dist: pysam
Requires-Dist: parasail (>=1.1.17)
